ovos_audio_plugin_spotify/__init__.py
ovos_audio_plugin_spotify/spotify_client.py
ovos_audio_plugin_spotify/version.py
ovos_audio_plugin_spotify-0.0.0a5.dist-info/LICENSE
ovos_audio_plugin_spotify-0.0.0a5.dist-info/METADATA
ovos_audio_plugin_spotify-0.0.0a5.dist-info/WHEEL
ovos_audio_plugin_spotify-0.0.0a5.dist-info/entry_points.txt
ovos_audio_plugin_spotify-0.0.0a5.dist-info/top_level.txt
ovos_audio_plugin_spotify-0.0.0a5.dist-info/RECORD
