Metadata-Version: 2.1
Name: ovos-audio-plugin-spotify
Version: 0.0.0a5
Summary: spotify plugin for ovos
Home-page: https://github.com/OpenVoiceOS/ovos-audio-plugin-spotify
Author: JarbasAi
Author-email: jarbasai@mailfence.com
License: Apache-2.0
Keywords: ovos audio plugin
Platform: UNKNOWN
Requires-Dist: spotipy
Requires-Dist: ovos-utils
Requires-Dist: ovos-backend-client
